LICENSE
MANIFEST.in
README.rst
muffin_memcached.py
requirements.txt
setup.py
muffin_memcached.egg-info/PKG-INFO
muffin_memcached.egg-info/SOURCES.txt
muffin_memcached.egg-info/dependency_links.txt
muffin_memcached.egg-info/requires.txt
muffin_memcached.egg-info/top_level.txt