Metadata-Version: 1.1
Name: muffin-memcached
Version: 0.0.1
Summary: UNKNOWN
Home-page: https://github.com/drgarcia1986/muffin-memcached
Author: Diego Garcia
Author-email: drgarcia1986@gmail.com
License: MIT
Keywords: asyncio,aiohttp,muffin,memcached
Platform: Any
Classifier: Development Status :: 4 - Beta
Classifier: Intended Audience :: Developers
Classifier: License :: OSI Approved :: BSD License
Classifier: Natural Language :: English
Classifier: Operating System :: OS Independent
Classifier: Programming Language :: Python :: 3
Classifier: Programming Language :: Python
Classifier: Topic :: Software Development :: Libraries :: Python Modules
Classifier: Topic :: Software Development :: Testing
Classifier: Topic :: Utilities
